pingthis/__init__.py
pingthis/__main__.py
pingthis-1.0.5.dist-info/METADATA
pingthis-1.0.5.dist-info/WHEEL
pingthis-1.0.5.dist-info/entry_points.txt
pingthis-1.0.5.dist-info/top_level.txt
pingthis-1.0.5.dist-info/RECORD
