Metadata-Version: 2.4
Name: pingthis
Version: 1.0.5
Summary: Terminal ping tool
Author: eytin
Classifier: Programming Language :: Python :: 3
Classifier: License :: OSI Approved :: MIT License
Requires-Dist: rich
Dynamic: author
Dynamic: classifier
Dynamic: description
Dynamic: description-content-type
Dynamic: requires-dist
Dynamic: summary
